[{"id":1,"status":"Scheduled","appointment":"2022-05-16T13:00:00","room":2,"doctor":"jovan","medicalRecord":"pera","anamnesis":"bbbbbbbbbbbbbbbbbbbbbbbbbb"},{"id":9,"status":"Scheduled","appointment":"2022-05-05T09:30:00","room":3,"doctor":"ivan","medicalRecord":"pera","anamnesis":""},{"id":12,"status":"Scheduled","appointment":"2022-05-04T09:45:00","room":3,"doctor":"ivan","medicalRecord":"pera","anamnesis":""},{"id":15,"status":"Scheduled","appointment":"2022-05-08T09:15:00","room":3,"doctor":"ivan","medicalRecord":"pera","anamnesis":""}]